README
setup.cfg
setup.py
django_render_load.egg-info/PKG-INFO
django_render_load.egg-info/SOURCES.txt
django_render_load.egg-info/dependency_links.txt
django_render_load.egg-info/entry_points.txt
django_render_load.egg-info/not-zip-safe
django_render_load.egg-info/top_level.txt
djangorenderload/__init__.py
djangorenderload/models.py
djangorenderload/tests.py
djangorenderload/views.py
djangorenderload/templatetags/__init__.py
djangorenderload/templatetags/load_object.py
djangorenderload/templatetags/render_object.py