Metadata-Version: 1.0
Name: django-render-load
Version: 0.0dev
Summary: Django template tags render_object and load_object grouped together.
Home-page: UNKNOWN
Author: Alexander Pugachev
Author-email: alexander.pugachev@gmail.com
License: UNKNOWN
Keywords: django template
Platform: UNKNOWN
